{"interfaceLanguages":{"swift":[{"children":[{"title":"Classes","type":"groupMarker"},{"children":[{"title":"Instance Methods","type":"groupMarker"},{"path":"\/documentation\/kingreceiver\/diskimagecache\/fetch(with:completion:)","title":"func fetch(with: URL, completion: (Data?) -> Void)","type":"method"}],"path":"\/documentation\/kingreceiver\/diskimagecache","title":"DiskImageCache","type":"class"},{"children":[{"title":"Enumerations","type":"groupMarker"},{"children":[{"title":"Enumeration Cases","type":"groupMarker"},{"path":"\/documentation\/kingreceiver\/imagecachefactory\/policy\/disk","title":"case disk","type":"case"},{"path":"\/documentation\/kingreceiver\/imagecachefactory\/policy\/memory","title":"case memory","type":"case"},{"path":"\/documentation\/kingreceiver\/imagecachefactory\/policy\/none","title":"case none","type":"case"},{"title":"Default Implementations","type":"groupMarker"},{"children":[{"title":"Operators","type":"groupMarker"},{"path":"\/documentation\/kingreceiver\/imagecachefactory\/policy\/!=(_:_:)","title":"static func != (Self, Self) -> Bool","type":"op"}],"path":"\/documentation\/kingreceiver\/imagecachefactory\/policy\/equatable-implementations","title":"Equatable Implementations","type":"symbol"}],"path":"\/documentation\/kingreceiver\/imagecachefactory\/policy","title":"ImageCacheFactory.Policy","type":"enum"}],"path":"\/documentation\/kingreceiver\/imagecachefactory","title":"ImageCacheFactory","type":"class"},{"children":[{"title":"Instance Methods","type":"groupMarker"},{"path":"\/documentation\/kingreceiver\/memoryimagecache\/fetch(with:completion:)","title":"func fetch(with: URL, completion: (Data?) -> Void)","type":"method"}],"path":"\/documentation\/kingreceiver\/memoryimagecache","title":"MemoryImageCache","type":"class"},{"children":[{"title":"Instance Methods","type":"groupMarker"},{"path":"\/documentation\/kingreceiver\/noneimagecache\/fetch(with:completion:)","title":"func fetch(with: URL, completion: (Data?) -> Void)","type":"method"}],"path":"\/documentation\/kingreceiver\/noneimagecache","title":"NoneImageCache","type":"class"},{"title":"Protocols","type":"groupMarker"},{"children":[{"title":"Instance Methods","type":"groupMarker"},{"path":"\/documentation\/kingreceiver\/imagecache\/fetch(with:completion:)","title":"func fetch(with: URL, completion: (Data?) -> Void)","type":"method"}],"path":"\/documentation\/kingreceiver\/imagecache","title":"ImageCache","type":"protocol"},{"children":[{"title":"Instance Properties","type":"groupMarker"},{"path":"\/documentation\/kingreceiver\/kingreceivercompatible\/kr","title":"var kr: KingReceiverWrapper<Self>","type":"property"}],"path":"\/documentation\/kingreceiver\/kingreceivercompatible","title":"KingReceiverCompatible","type":"protocol"},{"title":"Structures","type":"groupMarker"},{"children":[{"title":"Initializers","type":"groupMarker"},{"path":"\/documentation\/kingreceiver\/kingreceiver\/init()","title":"init()","type":"init"},{"title":"Instance Properties","type":"groupMarker"},{"path":"\/documentation\/kingreceiver\/kingreceiver\/text","title":"var text: String","type":"property"}],"path":"\/documentation\/kingreceiver\/kingreceiver","title":"KingReceiver","type":"struct"},{"children":[{"title":"Initializers","type":"groupMarker"},{"path":"\/documentation\/kingreceiver\/kingreceiverwrapper\/init(_:)","title":"init(Base)","type":"init"},{"title":"Instance Properties","type":"groupMarker"},{"path":"\/documentation\/kingreceiver\/kingreceiverwrapper\/base","title":"let base: Base","type":"property"},{"title":"Instance Methods","type":"groupMarker"},{"path":"\/documentation\/kingreceiver\/kingreceiverwrapper\/setimage(with:placeholder:indicator:cachepolicy:resizing:scale:)","title":"func setImage(with: String, placeholder: UIImage?, indicator: UIActivityIndicatorView, cachePolicy: ImageCacheFactory.Policy, resizing: Bool, scale: CGFloat)","type":"method"},{"path":"\/documentation\/kingreceiver\/kingreceiverwrapper\/setimage(with:placeholder:to:scale:)","title":"func setImage(with: Data, placeholder: UIImage?, to: CGSize, scale: CGFloat)","type":"method"}],"path":"\/documentation\/kingreceiver\/kingreceiverwrapper","title":"KingReceiverWrapper","type":"struct"}],"path":"\/documentation\/kingreceiver","title":"KingReceiver","type":"module"}]},"schemaVersion":{"major":0,"minor":1,"patch":1}}